liteium/__init__.py
liteium/main.py
liteium-1.0.6.dist-info/METADATA
liteium-1.0.6.dist-info/WHEEL
liteium-1.0.6.dist-info/top_level.txt
liteium-1.0.6.dist-info/RECORD
