Metadata-Version: 2.1
Name: liteium
Version: 1.0.6
Summary: Add Documentation
Home-page: https://github.com/XredaX/liteium
Author: El Bettioui Reda
Author-email: redaelbettioui@gmail.com
Classifier: Programming Language :: Python :: 3
Classifier: License :: OSI Approved :: MIT License
Classifier: Operating System :: OS Independent
Requires-Dist: selenium
